tiff_to_zarr/__init__.py
tiff_to_zarr/tiff_stack.py
tiff_to_zarr/tiff_to_zarr.py
tiff_to_zarr/tiff_volume.py
tiff_to_zarr-0.6.14.dist-info/LICENSE
tiff_to_zarr-0.6.14.dist-info/METADATA
tiff_to_zarr-0.6.14.dist-info/WHEEL
tiff_to_zarr-0.6.14.dist-info/entry_points.txt
tiff_to_zarr-0.6.14.dist-info/RECORD
