Metadata-Version: 2.3
Name: tiff-to-zarr
Version: 0.6.14
Summary: 
License: BSD 3-Clause License
Author: yurii_zubov
Requires-Python: >=3.10,<4.0
Classifier: License :: Other/Proprietary License
Classifier: Programming Language :: Python :: 3
Classifier: Programming Language :: Python :: 3.10
Classifier: Programming Language :: Python :: 3.11
Classifier: Programming Language :: Python :: 3.12
Classifier: Programming Language :: Python :: 3.13
Requires-Dist: asciitree (>=0.3.3,<0.4.0)
Requires-Dist: black (>=24.10.0,<25.0.0)
Requires-Dist: click (>=8.1.7,<9.0.0)
Requires-Dist: dask-jobqueue (==0.8.2)
Requires-Dist: imagecodecs (>=2024.1.1,<2025.0.0)
Requires-Dist: pyyaml (>=6.0.1,<7.0.0)
